nasa/__init__.py
nasa/_http.py
nasa/asset.py
nasa/client.py
nasa/enums.py
nasa/errors.py
nasa/_types/__init__.py
nasa/_types/apod_image.py
nasa/_types/epic_image.py
nasa/_types/log.py
nasasync-0.0.2a0.dist-info/LICENSE
nasasync-0.0.2a0.dist-info/METADATA
nasasync-0.0.2a0.dist-info/WHEEL
nasasync-0.0.2a0.dist-info/top_level.txt
nasasync-0.0.2a0.dist-info/RECORD
