Metadata-Version: 2.1
Name: nasasync
Version: 0.0.2a0
Summary: A python API wrapper for the NASA API
Author-email: Snipy7374 <snipy7374@gmail.com>
License: MIT
Project-URL: documentation, https://nasapy-a-nasa-api-python-wrapper.readthedocs.io/en/latest/index.html
Project-URL: changelog, https://nasapy-a-nasa-api-python-wrapper.readthedocs.io/en/beta/whats_new.html
Project-URL: repository, https://github.com/Snipy7374/nasa.py
Keywords: Nasa,Nasa.py,Nasa API
Classifier: Development Status :: 4 - Beta
Classifier: Intended Audience :: Developers
Classifier: License :: OSI Approved :: MIT License
Classifier: Natural Language :: English
Classifier: Operating System :: OS Independent
Classifier: Programming Language :: Python :: 3.10
Classifier: Programming Language :: Python :: 3.11
Classifier: Topic :: Internet
Classifier: Topic :: Software Development :: Libraries :: Python Modules
Classifier: Topic :: Utilities
Requires-Python: >=3.10
License-File: LICENSE
Requires-Dist: aiohttp
Requires-Dist: aiofiles
Requires-Dist: requests
